{
  "rooms": {
    "M14VyNeq": {
      "sources": {
        "https://www.facebook.com/groups/clubhousethailandcommunity/permalink/434243534296142/?comment_id=434255677628261": {
          "created_time": "2021-02-15T14:47:46+0000"
        }
      }
    },
    "ma6XEzZq": {
      "sources": {
        "https://www.facebook.com/groups/clubhousethailandcommunity/permalink/434661694254326/": {
          "created_time": "2021-02-16T10:44:51+0000"
        }
      }
    },
    "Md0ka5oq": {
      "sources": {
        "https://www.facebook.com/groups/clubhousethailandcommunity/permalink/434722637581565/": {
          "created_time": "2021-02-16T13:16:14+0000"
        }
      }
    },
    "MdR24Nyq": {
      "sources": {
        "https://twitter.com/kewpie_k/status/1364174741863469059": {
          "created_time": "2021-02-23T11:26:18.000Z"
        }
      }
    },
    "MO6wnBeQ": {
      "sources": {
        "https://twitter.com/walterjkun/status/1364222678463250434": {
          "created_time": "2021-02-23T14:36:47.000Z"
        }
      }
    },
    "xVJywEgQ": {
      "sources": {
        "https://twitter.com/victorishuman/status/1364224787074011147": {
          "created_time": "2021-02-23T14:45:09.000Z"
        },
        "https://twitter.com/tobyeve1/status/1364227493826203654": {
          "created_time": "2021-02-23T14:55:55.000Z"
        },
        "https://twitter.com/victorishuman/status/1364229988254326794": {
          "created_time": "2021-02-23T15:05:50.000Z"
        }
      }
    },
    "PA0XX4QQ": {
      "sources": {
        "https://twitter.com/Nt_Nutthiphat/status/1364238296805564418": {
          "created_time": "2021-02-23T15:38:50.000Z"
        },
        "https://twitter.com/Nt_Nutthiphat/status/1364238106241638400": {
          "created_time": "2021-02-23T15:38:05.000Z"
        }
      }
    },
    "xebZqJVQ": {
      "sources": {
        "https://twitter.com/itsn0rw0r/status/1364236511227469829": {
          "created_time": "2021-02-23T15:31:45.000Z"
        },
        "https://twitter.com/imyourjaysea/status/1364240196003241992": {
          "created_time": "2021-02-23T15:46:23.000Z"
        }
      }
    },
    "PAXv6LrQ": {
      "sources": {
        "https://twitter.com/guarounddaworld/status/1364241760596025350": {
          "created_time": "2021-02-23T15:52:36.000Z"
        }
      }
    },
    "xpjDKzGq": {
      "sources": {
        "https://twitter.com/jellyjubb/status/1364907655307792386": {
          "created_time": "2021-02-25T11:58:38.000Z"
        }
      }
    },
    "PQ2RygKQ": {
      "sources": {
        "https://twitter.com/belloworldD/status/1364916610910154752": {
          "created_time": "2021-02-25T12:34:13.000Z"
        },
        "https://twitter.com/belloworldD/status/1364916037934718976": {
          "created_time": "2021-02-25T12:31:57.000Z"
        },
        "https://twitter.com/belloworldD/status/1364918359599374342": {
          "created_time": "2021-02-25T12:41:10.000Z"
        },
        "https://twitter.com/belloworldD/status/1364926034735337481": {
          "created_time": "2021-02-25T13:11:40.000Z"
        }
      }
    },
    "xV8198yQ": {
      "sources": {
        "https://twitter.com/megnpa/status/1364929469786460160": {
          "created_time": "2021-02-25T13:25:19.000Z"
        },
        "https://twitter.com/megnpa/status/1364939020879335424": {
          "created_time": "2021-02-25T14:03:16.000Z"
        },
        "https://twitter.com/megnpa/status/1364943657208406016": {
          "created_time": "2021-02-25T14:21:41.000Z"
        },
        "https://twitter.com/megnpa/status/1364946231039057920": {
          "created_time": "2021-02-25T14:31:55.000Z"
        }
      }
    },
    "M1LDnRZQ": {
      "sources": {
        "https://twitter.com/pppppppluto/status/1364926752087109636": {
          "created_time": "2021-02-25T13:14:31.000Z"
        }
      }
    },
    "M17knroq": {
      "sources": {
        "https://twitter.com/kattpatcha/status/1364941622354472960": {
          "created_time": "2021-02-25T14:13:36.000Z"
        }
      }
    },
    "MKowkLWQ": {
      "sources": {
        "https://twitter.com/xxmmx__/status/1364943272766963716": {
          "created_time": "2021-02-25T14:20:10.000Z"
        }
      }
    },
    "xpA53zWq": {
      "sources": {
        "https://twitter.com/CBFOREVERSH/status/1364949115671617540": {
          "created_time": "2021-02-25T14:43:23.000Z"
        },
        "https://twitter.com/SuMi_AoR/status/1364950617937109004": {
          "created_time": "2021-02-25T14:49:21.000Z"
        }
      }
    },
    "MOvoYVnQ": {
      "sources": {
        "https://twitter.com/real90s_/status/1364953312580276228": {
          "created_time": "2021-02-25T15:00:03.000Z"
        }
      }
    },
    "MO825qRQ": {
      "sources": {
        "https://twitter.com/pavielin/status/1364952756511997952": {
          "created_time": "2021-02-25T14:57:51.000Z"
        }
      }
    },
    "MwJXjL7Q": {
      "sources": {
        "https://twitter.com/CharoenkwanS/status/1364997509781721091": {
          "created_time": "2021-02-25T17:55:41.000Z"
        },
        "https://twitter.com/majarern/status/1364997504580739074": {
          "created_time": "2021-02-25T17:55:40.000Z"
        },
        "https://twitter.com/CharoenkwanS/status/1365001050587942912": {
          "created_time": "2021-02-25T18:09:45.000Z"
        },
        "https://twitter.com/CharoenkwanS/status/1365003505925189633": {
          "created_time": "2021-02-25T18:19:31.000Z"
        },
        "https://twitter.com/majarern/status/1365003381459222529": {
          "created_time": "2021-02-25T18:19:01.000Z"
        },
        "https://twitter.com/CharoenkwanS/status/1365004965190672388": {
          "created_time": "2021-02-25T18:25:18.000Z"
        },
        "https://twitter.com/majarern/status/1365020667347755008": {
          "created_time": "2021-02-25T19:27:42.000Z"
        },
        "https://twitter.com/CharoenkwanS/status/1365022318053916672": {
          "created_time": "2021-02-25T19:34:16.000Z"
        },
        "https://twitter.com/CharoenkwanS/status/1365033167162277890": {
          "created_time": "2021-02-25T20:17:22.000Z"
        },
        "https://twitter.com/majarern/status/1365034112784867329": {
          "created_time": "2021-02-25T20:21:08.000Z"
        }
      }
    },
    "MdgjJr6q": {
      "sources": {
        "https://twitter.com/TB_141994/status/1365000722236903425": {
          "created_time": "2021-02-25T18:08:27.000Z"
        }
      }
    },
    "m2z5n9rq": {
      "sources": {
        "https://twitter.com/Topatimmm/status/1365164254626603011": {
          "created_time": "2021-02-26T04:58:16.000Z"
        }
      }
    },
    "Mw2Y9XEQ": {
      "sources": {
        "https://twitter.com/panwaisgod/status/1365294829538668546": {
          "created_time": "2021-02-26T13:37:07.000Z"
        }
      }
    },
    "PAKnbdzQ": {
      "sources": {
        "https://twitter.com/optimuxc/status/1365306207209091075": {
          "created_time": "2021-02-26T14:22:20.000Z"
        }
      }
    },
    "PN06Vkyq": {
      "sources": {
        "https://twitter.com/LATAEXBW/status/1365313247801266178": {
          "created_time": "2021-02-26T14:50:19.000Z"
        }
      }
    },
    "xla5J79q": {
      "sources": {
        "https://twitter.com/Ao_littleJTF/status/1365326297094791171": {
          "created_time": "2021-02-26T15:42:10.000Z"
        }
      }
    },
    "PQNKKrAQ": {
      "sources": {
        "https://twitter.com/panwaisgod/status/1365555357259472897": {
          "created_time": "2021-02-27T06:52:22.000Z"
        },
        "https://twitter.com/panwaisgod/status/1365556476673024003": {
          "created_time": "2021-02-27T06:56:49.000Z"
        },
        "https://twitter.com/panwaisgod/status/1365615868697145344": {
          "created_time": "2021-02-27T10:52:49.000Z"
        }
      }
    },
    "M1Kz23lq": {
      "sources": {
        "https://twitter.com/gigigiena/status/1365691187672285192": {
          "created_time": "2021-02-27T15:52:07.000Z"
        },
        "https://twitter.com/gigigiena/status/1365690185858473985": {
          "created_time": "2021-02-27T15:48:08.000Z"
        },
        "https://twitter.com/gigigiena/status/1365691855317295104": {
          "created_time": "2021-02-27T15:54:46.000Z"
        }
      }
    },
    "PQNgKrWQ": {
      "sources": {
        "https://twitter.com/bptsagsz/status/1365701841929953283": {
          "created_time": "2021-02-27T16:34:27.000Z"
        },
        "https://twitter.com/wjgfio19/status/1365718012045660160": {
          "created_time": "2021-02-27T17:38:42.000Z"
        }
      }
    },
    "M5zR5Vrq": {
      "sources": {
        "https://twitter.com/Khunjib69/status/1365708118080974855": {
          "created_time": "2021-02-27T16:59:23.000Z"
        }
      }
    },
    "Mwak3vlQ": {
      "sources": {
        "https://twitter.com/xianbingg/status/1365715940239810566": {
          "created_time": "2021-02-27T17:30:28.000Z"
        },
        "https://twitter.com/anatomybaconn/status/1365737242208071682": {
          "created_time": "2021-02-27T18:55:07.000Z"
        }
      }
    },
    "M1zqdKnq": {
      "sources": {
        "https://twitter.com/SongSaLueng/status/1365939800155459589": {
          "created_time": "2021-02-28T08:20:00.000Z"
        }
      }
    },
    "MOBXQn6Q": {
      "sources": {
        "https://twitter.com/LATAEXBW/status/1365992003071143943": {
          "created_time": "2021-02-28T11:47:27.000Z"
        }
      }
    },
    "PNj0W5zq": {
      "sources": {
        "https://twitter.com/pdd____/status/1366037368843640842": {
          "created_time": "2021-02-28T14:47:43.000Z",
          "retweet_count": 0,
          "favorite_count": 1
        },
        "https://twitter.com/pdd____/status/1366036787563401218": {
          "created_time": "2021-02-28T14:45:24.000Z",
          "retweet_count": 0,
          "favorite_count": 0
        },
        "https://twitter.com/pdd____/status/1366050670504079361": {
          "created_time": "2021-02-28T15:40:34.000Z",
          "retweet_count": 0,
          "favorite_count": 0
        },
        "https://twitter.com/pdd____/status/1366057097859768325": {
          "created_time": "2021-02-28T16:06:06.000Z",
          "retweet_count": 0,
          "favorite_count": 1
        }
      }
    },
    "M1OBw9XQ": {
      "sources": {
        "https://twitter.com/sanxz57/status/1366051604151947268": {
          "created_time": "2021-02-28T15:44:17.000Z",
          "retweet_count": 0,
          "favorite_count": 0
        }
      }
    },
    "P9K74BaQ": {
      "sources": {
        "https://twitter.com/Croissaaant/status/1366263308852940800": {
          "created_time": "2021-03-01T05:45:31.000Z",
          "retweet_count": 0,
          "favorite_count": 0
        },
        "https://twitter.com/Topatimmm/status/1366276880609931267": {
          "created_time": "2021-03-01T06:39:27.000Z",
          "retweet_count": 0,
          "favorite_count": 0
        }
      }
    },
    "PAJzQNZQ": {
      "sources": {
        "https://twitter.com/anueng_/status/1366391865906368512": {
          "created_time": "2021-03-01T14:16:21.000Z",
          "retweet_count": 1,
          "favorite_count": 0
        },
        "https://twitter.com/xxiamqueenxx/status/1366392632868360195": {
          "created_time": "2021-03-01T14:19:24.000Z",
          "retweet_count": 0,
          "favorite_count": 1
        }
      }
    },
    "PNjDl8eq": {
      "sources": {
        "https://twitter.com/Kulaynat1995/status/1366409310121590787": {
          "created_time": "2021-03-01T15:25:40.000Z",
          "retweet_count": 0,
          "favorite_count": 0
        }
      }
    },
    "MwwyyEaQ": {
      "sources": {
        "https://twitter.com/Tualek29/status/1366473939329843201": {
          "created_time": "2021-03-01T19:42:29.000Z",
          "retweet_count": 0,
          "favorite_count": 0
        }
      }
    },
    "PAJaG8kQ": {
      "sources": {
        "https://twitter.com/MeBeforeU2/status/1366708097541042187": {
          "created_time": "2021-03-02T11:12:57.000Z",
          "retweet_count": 0,
          "favorite_count": 0
        },
        "https://twitter.com/Orrism/status/1366730594298724354": {
          "created_time": "2021-03-02T12:42:20.000Z",
          "retweet_count": 9,
          "favorite_count": 2
        }
      }
    },
    "xpQROv8q": {
      "sources": {
        "https://twitter.com/yselpam/status/1366727121331122182": {
          "created_time": "2021-03-02T12:28:32.000Z",
          "retweet_count": 2,
          "favorite_count": 0
        }
      }
    },
    "M17aoJ2q": {
      "sources": {
        "https://twitter.com/npingprink1/status/1366743839797485574": {
          "created_time": "2021-03-02T13:34:58.000Z",
          "retweet_count": 0,
          "favorite_count": 0
        },
        "https://twitter.com/MeBeforeU2/status/1366749923987755012": {
          "created_time": "2021-03-02T13:59:09.000Z",
          "retweet_count": 0,
          "favorite_count": 0
        },
        "https://twitter.com/CHXICHIX/status/1366749601416404992": {
          "created_time": "2021-03-02T13:57:52.000Z",
          "retweet_count": 0,
          "favorite_count": 0
        }
      }
    },
    "xp91OZ3q": {
      "sources": {
        "https://twitter.com/SuMi_AoR/status/1366758528057184256": {
          "created_time": "2021-03-02T14:33:20.000Z",
          "retweet_count": 1,
          "favorite_count": 0
        },
        "https://twitter.com/mayonsky/status/1366758180747763712": {
          "created_time": "2021-03-02T14:31:58.000Z",
          "retweet_count": 1,
          "favorite_count": 0
        },
        "https://twitter.com/SAaaa_saasas/status/1366757998387888130": {
          "created_time": "2021-03-02T14:31:14.000Z",
          "retweet_count": 0,
          "favorite_count": 0
        },
        "https://twitter.com/ChonladaPong/status/1366786462172073991": {
          "created_time": "2021-03-02T16:24:20.000Z",
          "retweet_count": 2,
          "favorite_count": 0
        }
      }
    },
    "m2zeJJ8q": {
      "sources": {
        "https://twitter.com/18bearx/status/1366762137813573634": {
          "created_time": "2021-03-02T14:47:41.000Z",
          "retweet_count": 0,
          "favorite_count": 0
        }
      }
    },
    "M5eoZKKq": {
      "sources": {
        "https://twitter.com/nongpoploy/status/1366766982670999556": {
          "created_time": "2021-03-02T15:06:56.000Z",
          "retweet_count": 0,
          "favorite_count": 0
        }
      }
    },
    "P9WNvN6Q": {
      "sources": {
        "https://twitter.com/PNSNTK/status/1366805564215320580": {
          "created_time": "2021-03-02T17:40:15.000Z",
          "retweet_count": 1,
          "favorite_count": 1
        }
      }
    },
    "xna5XB6Q": {
      "sources": {
        "https://twitter.com/phope_ndumpling/status/1366823220754542592": {
          "created_time": "2021-03-02T18:50:24.000Z",
          "retweet_count": 0,
          "favorite_count": 0
        }
      }
    },
    "MdO8O5jq": {
      "sources": {
        "https://twitter.com/lovelyeverydayx/status/1367106834750873602": {
          "created_time": "2021-03-03T13:37:23.000Z",
          "retweet_count": 0,
          "favorite_count": 0
        }
      }
    },
    "MwneKylQ": {
      "sources": {
        "https://thaiclubhouse.web.app/submit.html": {
          "created_time": "2021-03-03T15:43:53.000Z"
        }
      }
    },
    "PNy1vGAq": {
      "sources": {
        "https://twitter.com/kjm_suhoexoii/status/1367180234311618565": {
          "created_time": "2021-03-03T18:29:03.000Z",
          "retweet_count": 1,
          "favorite_count": 0
        }
      }
    },
    "Mdjv8v1q": {
      "sources": {
        "https://twitter.com/deary2543/status/1367486707210272768": {
          "created_time": "2021-03-04T14:46:52.000Z",
          "retweet_count": 0,
          "favorite_count": 0
        }
      }
    },
    "mav4zzVq": {
      "sources": {
        "https://twitter.com/Biitonntoey/status/1367502313296953352": {
          "created_time": "2021-03-04T15:48:53.000Z",
          "retweet_count": 1,
          "favorite_count": 0
        },
        "https://twitter.com/PeachNS3/status/1367510560913321984": {
          "created_time": "2021-03-04T16:21:39.000Z",
          "retweet_count": 1,
          "favorite_count": 0
        }
      }
    },
    "xVbr5W7Q": {
      "sources": {
        "https://twitter.com/moohouseCH/status/1367525252901654530": {
          "created_time": "2021-03-04T17:20:02.000Z",
          "retweet_count": 7,
          "favorite_count": 3
        }
      }
    },
    "xeRgVy8Q": {
      "sources": {
        "https://twitter.com/real90s_/status/1367839925329043466": {
          "created_time": "2021-03-05T14:10:26.000Z",
          "retweet_count": 0,
          "favorite_count": 0
        },
        "https://twitter.com/real90s_/status/1367847371279757315": {
          "created_time": "2021-03-05T14:40:01.000Z",
          "retweet_count": 0,
          "favorite_count": 1
        },
        "https://twitter.com/flukcaf/status/1367868046270812165": {
          "created_time": "2021-03-05T16:02:10.000Z",
          "retweet_count": 0,
          "favorite_count": 0
        }
      }
    },
    "P9vy3N5Q": {
      "sources": {
        "https://twitter.com/ssnowmoon/status/1367839703693598721": {
          "created_time": "2021-03-05T14:09:33.000Z",
          "retweet_count": 1,
          "favorite_count": 0
        }
      }
    },
    "MdjN9vXq": {
      "sources": {
        "https://twitter.com/spwannacry/status/1367868221223706626": {
          "created_time": "2021-03-05T16:02:52.000Z",
          "retweet_count": 0,
          "favorite_count": 0
        }
      }
    },
    "xlOvvnwq": {
      "sources": {
        "https://twitter.com/yob1622/status/1367874593747333120": {
          "created_time": "2021-03-05T16:28:11.000Z",
          "retweet_count": 0,
          "favorite_count": 1
        }
      }
    },
    "M1K9pb1q": {
      "sources": {
        "https://twitter.com/f_ffame_f/status/1367881358601646081": {
          "created_time": "2021-03-05T16:55:04.000Z",
          "retweet_count": 0,
          "favorite_count": 0
        }
      }
    },
    "PN030eyq": {
      "sources": {
        "https://twitter.com/No_name_ns/status/1367886157527183361": {
          "created_time": "2021-03-05T17:14:08.000Z",
          "retweet_count": 0,
          "favorite_count": 1
        }
      }
    },
    "Mww7nwlQ": {
      "sources": {
        "https://twitter.com/unname_9/status/1367913097902522368": {
          "created_time": "2021-03-05T19:01:11.000Z",
          "retweet_count": 0,
          "favorite_count": 0
        }
      }
    },
    "M1OeB7Nq": {
      "sources": {
        "https://twitter.com/ghostmouse07/status/1368170749417172998": {
          "created_time": "2021-03-06T12:05:00.000Z",
          "retweet_count": 0,
          "favorite_count": 0
        }
      }
    },
    "PNbZ2k8q": {
      "sources": {
        "https://twitter.com/jaoQBbz9U1kxAHF/status/1368201024456978440": {
          "created_time": "2021-03-06T14:05:18.000Z",
          "retweet_count": 0,
          "favorite_count": 1
        }
      }
    },
    "xeL1pRoQ": {
      "sources": {
        "https://twitter.com/mysundaee/status/1368391669180104705": {
          "created_time": "2021-03-07T02:42:52.000Z",
          "retweet_count": 1,
          "favorite_count": 0
        }
      }
    },
    "PN59l71q": {
      "sources": {
        "https://twitter.com/ploypotter/status/1368551087133790212": {
          "created_time": "2021-03-07T13:16:20.000Z",
          "retweet_count": 5,
          "favorite_count": 0
        }
      }
    },
    "xpep7vpq": {
      "sources": {
        "https://twitter.com/Aummubet/status/1368611376214675456": {
          "created_time": "2021-03-07T17:15:54.000Z",
          "retweet_count": 3,
          "favorite_count": 1
        }
      }
    },
    "mJokDYQQ": {
      "sources": {
        "https://twitter.com/mumumuplz/status/1368648768128647168": {
          "created_time": "2021-03-07T19:44:29.000Z",
          "retweet_count": 0,
          "favorite_count": 0
        },
        "https://twitter.com/qkenjix/status/1368650245857452033": {
          "created_time": "2021-03-07T19:50:21.000Z",
          "retweet_count": 0,
          "favorite_count": 0
        }
      }
    },
    "PQnyQ9nQ": {
      "sources": {
        "https://twitter.com/democracy_rb/status/1368927313191002117": {
          "created_time": "2021-03-08T14:11:19.000Z",
          "retweet_count": 1,
          "favorite_count": 0
        },
        "https://twitter.com/sarinubia/status/1368936811217649672": {
          "created_time": "2021-03-08T14:49:04.000Z",
          "retweet_count": 2,
          "favorite_count": 0
        },
        "https://twitter.com/rosemiyuke/status/1368942526107820034": {
          "created_time": "2021-03-08T15:11:46.000Z",
          "retweet_count": 0,
          "favorite_count": 0
        }
      }
    },
    "xV0b6o5Q": {
      "sources": {
        "https://twitter.com/Armychirat/status/1368928174608818177": {
          "created_time": "2021-03-08T14:14:44.000Z",
          "retweet_count": 0,
          "favorite_count": 0
        },
        "https://twitter.com/lnelnejir/status/1368927662333325317": {
          "created_time": "2021-03-08T14:12:42.000Z",
          "retweet_count": 0,
          "favorite_count": 0
        }
      }
    },
    "m2ENeadq": {
      "sources": {
        "https://twitter.com/qnucy_/status/1368968720719089673": {
          "created_time": "2021-03-08T16:55:51.000Z",
          "retweet_count": 1,
          "favorite_count": 0
        },
        "https://twitter.com/qnucy_/status/1368971181248761860": {
          "created_time": "2021-03-08T17:05:38.000Z",
          "retweet_count": 0,
          "favorite_count": 0
        },
        "https://twitter.com/qnucy_/status/1368976115990110208": {
          "created_time": "2021-03-08T17:25:15.000Z",
          "retweet_count": 0,
          "favorite_count": 0
        }
      }
    },
    "Mwr297eQ": {
      "sources": {
        "https://twitter.com/rosemiyuke/status/1369211726072217600": {
          "created_time": "2021-03-09T09:01:28.000Z",
          "retweet_count": 0,
          "favorite_count": 1
        },
        "https://twitter.com/Karrypx_/status/1369245074186526725": {
          "created_time": "2021-03-09T11:13:59.000Z",
          "retweet_count": 0,
          "favorite_count": 0
        },
        "https://twitter.com/Kr5iUdXkERjZJg1/status/1369259592589348872": {
          "created_time": "2021-03-09T12:11:41.000Z",
          "retweet_count": 0,
          "favorite_count": 0
        }
      }
    },
    "M5Ywe0Kq": {
      "sources": {
        "https://twitter.com/iseayoun/status/1369296739056820224": {
          "created_time": "2021-03-09T14:39:17.000Z",
          "retweet_count": 0,
          "favorite_count": 0
        }
      }
    },
    "PNzLNejq": {
      "sources": {
        "https://twitter.com/wilysmf/status/1369302199851958279": {
          "created_time": "2021-03-09T15:00:59.000Z",
          "retweet_count": 0,
          "favorite_count": 1
        }
      }
    },
    "M5K76rRq": {
      "sources": {
        "https://twitter.com/sugaho3/status/1369328361034616842": {
          "created_time": "2021-03-09T16:44:56.000Z",
          "retweet_count": 0,
          "favorite_count": 0
        }
      }
    },
    "m2j3EXzq": {
      "sources": {
        "https://twitter.com/rosemiyuke/status/1369441489588264973": {
          "created_time": "2021-03-10T00:14:28.000Z",
          "retweet_count": 0,
          "favorite_count": 0
        },
        "https://twitter.com/Topatimmm/status/1369471649305665541": {
          "created_time": "2021-03-10T02:14:19.000Z",
          "retweet_count": 0,
          "favorite_count": 1
        }
      }
    },
    "Md3eG1Wq": {
      "sources": {
        "https://twitter.com/itSunShine_s/status/1369691928522989572": {
          "created_time": "2021-03-10T16:49:38.000Z",
          "retweet_count": 0,
          "favorite_count": 0
        },
        "https://twitter.com/itSunShine_s/status/1369695266362695680": {
          "created_time": "2021-03-10T17:02:53.000Z",
          "retweet_count": 0,
          "favorite_count": 0
        },
        "https://twitter.com/itSunShine_s/status/1369696758612123649": {
          "created_time": "2021-03-10T17:08:49.000Z",
          "retweet_count": 0,
          "favorite_count": 0
        },
        "https://twitter.com/itSunShine_s/status/1369698973720707079": {
          "created_time": "2021-03-10T17:17:37.000Z",
          "retweet_count": 0,
          "favorite_count": 0
        },
        "https://twitter.com/itSunShine_s/status/1369700507283976196": {
          "created_time": "2021-03-10T17:23:43.000Z",
          "retweet_count": 0,
          "favorite_count": 0
        },
        "https://twitter.com/itSunShine_s/status/1369703384756887556": {
          "created_time": "2021-03-10T17:35:09.000Z",
          "retweet_count": 0,
          "favorite_count": 1
        },
        "https://twitter.com/itSunShine_s/status/1369705167965224960": {
          "created_time": "2021-03-10T17:42:14.000Z",
          "retweet_count": 0,
          "favorite_count": 0
        },
        "https://twitter.com/itSunShine_s/status/1369714151409393664": {
          "created_time": "2021-03-10T18:17:56.000Z",
          "retweet_count": 0,
          "favorite_count": 0
        },
        "https://twitter.com/itSunShine_s/status/1369716134467923972": {
          "created_time": "2021-03-10T18:25:49.000Z",
          "retweet_count": 0,
          "favorite_count": 0
        }
      }
    },
    "mZW3L5vQ": {
      "sources": {
        "https://twitter.com/khunnanarak/status/1370050418483417090": {
          "created_time": "2021-03-11T16:34:08.000Z",
          "retweet_count": 0,
          "favorite_count": 0
        },
        "https://twitter.com/khunnanarak/status/1370054897840705539": {
          "created_time": "2021-03-11T16:51:56.000Z",
          "retweet_count": 0,
          "favorite_count": 0
        }
      }
    },
    "MOpR16QQ": {
      "sources": {
        "https://twitter.com/Pink_Siripipat/status/1370180382717480961": {
          "created_time": "2021-03-12T01:10:34.000Z",
          "retweet_count": 6,
          "favorite_count": 8
        }
      }
    },
    "MwabWYbQ": {
      "sources": {
        "https://twitter.com/fyfubu_er/status/1370732424611598336": {
          "created_time": "2021-03-13T13:44:11.000Z",
          "retweet_count": 2,
          "favorite_count": 0
        }
      }
    },
    "M1WDvNkQ": {
      "sources": {
        "https://twitter.com/panwaisgod/status/1371444864794071041": {
          "created_time": "2021-03-15T12:55:10.000Z",
          "retweet_count": 0,
          "favorite_count": 0
        }
      }
    },
    "xpWbjJQq": {
      "sources": {
        "https://twitter.com/wrksang/status/1371881771562790912": {
          "created_time": "2021-03-16T17:51:17.000Z",
          "retweet_count": 0,
          "favorite_count": 0
        }
      }
    },
    "M1WWLXRq": {
      "sources": {
        "https://twitter.com/faifinite/status/1372209000268263424": {
          "created_time": "2021-03-17T15:31:34.000Z",
          "retweet_count": 0,
          "favorite_count": 0
        }
      }
    },
    "M1WygAJQ": {
      "sources": {
        "https://twitter.com/seonminxqstorex/status/1372219618849390595": {
          "created_time": "2021-03-17T16:13:46.000Z",
          "retweet_count": 0,
          "favorite_count": 0
        }
      }
    },
    "m21ej0rq": {
      "sources": {
        "https://twitter.com/dotenblessme/status/1373302274479464448": {
          "created_time": "2021-03-20T15:55:51.000Z",
          "retweet_count": 0,
          "favorite_count": 0
        }
      }
    },
    "m22j2Xnq": {
      "sources": {
        "https://twitter.com/syswww_/status/1374713495111954439": {
          "created_time": "2021-03-24T13:23:32.000Z",
          "retweet_count": 0,
          "favorite_count": 0
        }
      }
    },
    "MKjWdvKQ": {
      "sources": {
        "https://twitter.com/Pink_Siripipat/status/1376132665296842757": {
          "created_time": "2021-03-28T11:22:49.000Z",
          "retweet_count": 1,
          "favorite_count": 4
        },
        "https://twitter.com/sosweetsally/status/1376158434337325057": {
          "created_time": "2021-03-28T13:05:13.000Z",
          "retweet_count": 0,
          "favorite_count": 1
        }
      }
    },
    "MK5Al5oQ": {
      "sources": {
        "https://twitter.com/suchitra0183/status/1376916721181712387": {
          "created_time": "2021-03-30T15:18:22.000Z",
          "retweet_count": 0,
          "favorite_count": 0
        }
      }
    },
    "xlBRdp7q": {
      "sources": {
        "https://twitter.com/tewlyrally/status/1378083331506536448": {
          "created_time": "2021-04-02T20:34:04.000Z",
          "retweet_count": 0,
          "favorite_count": 0
        }
      }
    },
    "M1K3j9NQ": {
      "sources": {
        "https://twitter.com/nttarot/status/1378311397277229058": {
          "created_time": "2021-04-03T11:40:19.000Z",
          "retweet_count": 6,
          "favorite_count": 0
        }
      }
    },
    "MwVJZOqQ": {
      "sources": {
        "https://twitter.com/khunnanarak/status/1380549520027574278": {
          "created_time": "2021-04-09T15:53:49.000Z",
          "retweet_count": 0,
          "favorite_count": 0
        },
        "https://twitter.com/khunnanarak/status/1380548761894588416": {
          "created_time": "2021-04-09T15:50:48.000Z",
          "retweet_count": 0,
          "favorite_count": 0
        },
        "https://twitter.com/khunnanarak/status/1380555547125030917": {
          "created_time": "2021-04-09T16:17:46.000Z",
          "retweet_count": 0,
          "favorite_count": 0
        }
      }
    },
    "MwWyYlGQ": {
      "sources": {
        "https://twitter.com/mafav16/status/1381659284409217024": {
          "created_time": "2021-04-12T17:23:38.000Z",
          "retweet_count": 0,
          "favorite_count": 0
        }
      }
    },
    "xpj3V7nq": {
      "sources": {
        "https://twitter.com/pavielin/status/1383061579848065030": {
          "created_time": "2021-04-16T14:15:51.000Z",
          "retweet_count": 0,
          "favorite_count": 5
        }
      }
    },
    "MK3lVy2Q": {
      "sources": {
        "https://twitter.com/beam1743/status/1383066723146866688": {
          "created_time": "2021-04-16T14:36:17.000Z",
          "retweet_count": 0,
          "favorite_count": 0
        }
      }
    },
    "MOKy348Q": {
      "sources": {
        "https://twitter.com/meenanuchbaa/status/1383454818883174411": {
          "created_time": "2021-04-17T16:18:26.000Z",
          "retweet_count": 0,
          "favorite_count": 0
        }
      }
    },
    "xlO1ZyNq": {
      "sources": {
        "https://twitter.com/Pink_Siripipat/status/1383955270598987784": {
          "created_time": "2021-04-19T01:27:03.000Z",
          "retweet_count": 4,
          "favorite_count": 10
        }
      }
    },
    "M1L5jjDQ": {
      "sources": {
        "https://twitter.com/OldMan_b1/status/1384131629614997508": {
          "created_time": "2021-04-19T13:07:51.000Z",
          "retweet_count": 1,
          "favorite_count": 1
        }
      }
    },
    "PAKYB35Q": {
      "sources": {
        "https://twitter.com/August_sonteen/status/1412451011457781762": {
          "created_time": "2021-07-06T16:38:57.000Z",
          "retweet_count": 0,
          "favorite_count": 0
        }
      }
    },
    "Mww4aywQ": {
      "sources": {
        "https://twitter.com/belloworldD/status/1412452520446730241": {
          "created_time": "2021-07-06T16:44:57.000Z",
          "retweet_count": 0,
          "favorite_count": 0
        }
      }
    },
    "MOGlyOZQ": {
      "sources": {
        "https://twitter.com/hoksingha/status/1412730115121836034": {
          "created_time": "2021-07-07T11:08:01.000Z",
          "retweet_count": 0,
          "favorite_count": 1
        },
        "https://twitter.com/selfcircled/status/1412731831145820172": {
          "created_time": "2021-07-07T11:14:50.000Z",
          "retweet_count": 3,
          "favorite_count": 8
        },
        "https://twitter.com/hoksingha/status/1412734515307372545": {
          "created_time": "2021-07-07T11:25:30.000Z",
          "retweet_count": 0,
          "favorite_count": 2
        }
      }
    },
    "mJn3G3QQ": {
      "sources": {
        "https://twitter.com/Clubmouths/status/1413511552137764866": {
          "created_time": "2021-07-09T14:53:10.000Z",
          "retweet_count": 2,
          "favorite_count": 0
        }
      }
    },
    "M5v3lNWq": {
      "sources": {
        "https://twitter.com/iluvujunghwan/status/1414227490197831680": {
          "created_time": "2021-07-11T14:18:03.000Z",
          "retweet_count": 0,
          "favorite_count": 0
        }
      }
    },
    "xVra2jdQ": {
      "sources": {
        "https://twitter.com/tukzerotuk/status/1414559370868715528": {
          "created_time": "2021-07-12T12:16:49.000Z",
          "retweet_count": 0,
          "favorite_count": 4
        },
        "https://twitter.com/_dark_zone/status/1414559469103501319": {
          "created_time": "2021-07-12T12:17:13.000Z",
          "retweet_count": 0,
          "favorite_count": 4
        },
        "https://twitter.com/thaiunityclub/status/1414561276500533252": {
          "created_time": "2021-07-12T12:24:24.000Z",
          "retweet_count": 6,
          "favorite_count": 6
        }
      }
    },
    "M1QEr9kq": {
      "sources": {
        "https://twitter.com/brmamam/status/1414599568897970177": {
          "created_time": "2021-07-12T14:56:33.000Z",
          "retweet_count": 0,
          "favorite_count": 0
        }
      }
    },
    "ma5pvobq": {
      "sources": {
        "https://twitter.com/OldMan_b1/status/1415515377694478341": {
          "created_time": "2021-07-15T03:35:39.000Z",
          "retweet_count": 0,
          "favorite_count": 1
        }
      }
    },
    "MOpk39eQ": {
      "sources": {
        "https://twitter.com/bbesttyty/status/1416076755920506888": {
          "created_time": "2021-07-16T16:46:22.000Z",
          "retweet_count": 0,
          "favorite_count": 0
        }
      }
    },
    "MwEaNVjQ": {
      "sources": {
        "https://twitter.com/thanuchsss/status/1416408038701862913": {
          "created_time": "2021-07-17T14:42:46.000Z",
          "retweet_count": 0,
          "favorite_count": 0
        }
      }
    },
    "PAa1p3VQ": {
      "sources": {
        "https://twitter.com/themaompss/status/1416414945311297542": {
          "created_time": "2021-07-17T15:10:13.000Z",
          "retweet_count": 1,
          "favorite_count": 0
        }
      }
    },
    "PNzWLq6q": {
      "sources": {
        "https://twitter.com/ivaderlll/status/1416784384556822529": {
          "created_time": "2021-07-18T15:38:14.000Z",
          "retweet_count": 0,
          "favorite_count": 0
        }
      }
    },
    "M168weJq": {
      "sources": {
        "https://twitter.com/we_meat/status/1418180417228660740": {
          "created_time": "2021-07-22T12:05:34.000Z",
          "retweet_count": 1,
          "favorite_count": 1
        }
      }
    },
    "P90kNqQQ": {
      "sources": {
        "https://twitter.com/hoksingha/status/1418580834366361603": {
          "created_time": "2021-07-23T14:36:41.000Z",
          "retweet_count": 0,
          "favorite_count": 1
        },
        "https://twitter.com/Kunni_Pa/status/1418586935077920774": {
          "created_time": "2021-07-23T15:00:56.000Z",
          "retweet_count": 0,
          "favorite_count": 0
        },
        "https://twitter.com/chaeaa17/status/1418589452667023377": {
          "created_time": "2021-07-23T15:10:56.000Z",
          "retweet_count": 0,
          "favorite_count": 2
        },
        "https://twitter.com/FREED0MnotFree/status/1418589854443610112": {
          "created_time": "2021-07-23T15:12:32.000Z",
          "retweet_count": 0,
          "favorite_count": 1
        }
      }
    },
    "maQJED4q": {
      "sources": {
        "https://twitter.com/yellotomyfellow/status/1418944653391454211": {
          "created_time": "2021-07-24T14:42:22.000Z",
          "retweet_count": 1,
          "favorite_count": 0
        }
      }
    },
    "mavA7vkq": {
      "sources": {
        "https://twitter.com/prdemocracy/status/1419232929406865408": {
          "created_time": "2021-07-25T09:47:53.000Z",
          "retweet_count": 0,
          "favorite_count": 1
        },
        "https://twitter.com/prdemocracy/status/1419234487125176327": {
          "created_time": "2021-07-25T09:54:04.000Z",
          "retweet_count": 0,
          "favorite_count": 0
        },
        "https://twitter.com/prdemocracy/status/1419234445161209856": {
          "created_time": "2021-07-25T09:53:54.000Z",
          "retweet_count": 0,
          "favorite_count": 0
        },
        "https://twitter.com/prdemocracy/status/1419234404807761924": {
          "created_time": "2021-07-25T09:53:44.000Z",
          "retweet_count": 0,
          "favorite_count": 1
        },
        "https://twitter.com/prdemocracy/status/1419234097008824326": {
          "created_time": "2021-07-25T09:52:31.000Z",
          "retweet_count": 4,
          "favorite_count": 9
        },
        "https://twitter.com/prdemocracy/status/1419233912287469572": {
          "created_time": "2021-07-25T09:51:47.000Z",
          "retweet_count": 0,
          "favorite_count": 0
        },
        "https://twitter.com/prdemocracy/status/1419233860500393986": {
          "created_time": "2021-07-25T09:51:35.000Z",
          "retweet_count": 0,
          "favorite_count": 0
        },
        "https://twitter.com/prdemocracy/status/1419233795673268224": {
          "created_time": "2021-07-25T09:51:19.000Z",
          "retweet_count": 0,
          "favorite_count": 0
        },
        "https://twitter.com/prdemocracy/status/1419233406093709316": {
          "created_time": "2021-07-25T09:49:46.000Z",
          "retweet_count": 0,
          "favorite_count": 0
        },
        "https://twitter.com/prdemocracy/status/1419233343946719238": {
          "created_time": "2021-07-25T09:49:31.000Z",
          "retweet_count": 0,
          "favorite_count": 0
        },
        "https://twitter.com/prdemocracy/status/1419234531148660744": {
          "created_time": "2021-07-25T09:54:14.000Z",
          "retweet_count": 0,
          "favorite_count": 0
        }
      }
    },
    "MK5dl6pQ": {
      "sources": {
        "https://twitter.com/kcurran77/status/1419282707511746564": {
          "created_time": "2021-07-25T13:05:41.000Z",
          "retweet_count": 1,
          "favorite_count": 7
        }
      }
    },
    "PN6Bw7Wq": {
      "sources": {
        "https://twitter.com/rrose_rosee/status/1419323367664939009": {
          "created_time": "2021-07-25T15:47:15.000Z",
          "retweet_count": 0,
          "favorite_count": 0
        }
      }
    },
    "P9eJkOgQ": {
      "sources": {
        "https://twitter.com/Slavebrightwin/status/1419558827586854915": {
          "created_time": "2021-07-26T07:22:53.000Z",
          "retweet_count": 0,
          "favorite_count": 0
        }
      }
    },
    "m2zXGJjq": {
      "sources": {
        "https://twitter.com/mimisisinKorea_/status/1420374198308933633": {
          "created_time": "2021-07-28T13:22:52.000Z",
          "retweet_count": 4,
          "favorite_count": 0
        }
      }
    },
    "M5Y6n1eq": {
      "sources": {
        "https://twitter.com/fitnesswla/status/1423261797382074376": {
          "created_time": "2021-08-05T12:37:10.000Z",
          "retweet_count": 0,
          "favorite_count": 0
        }
      }
    },
    "PAjGD3wQ": {
      "sources": {
        "https://twitter.com/sstkm_q/status/1423318050124697601": {
          "created_time": "2021-08-05T16:20:41.000Z",
          "retweet_count": 0,
          "favorite_count": 0
        }
      }
    },
    "PQDwRK9Q": {
      "sources": {
        "https://twitter.com/sosweetsally/status/1423513245554397190": {
          "created_time": "2021-08-06T05:16:19.000Z",
          "retweet_count": 0,
          "favorite_count": 1
        }
      }
    },
    "mJz73RoQ": {
      "sources": {
        "https://twitter.com/Pink_Siripipat/status/1423816528609234946": {
          "created_time": "2021-08-07T01:21:28.000Z",
          "retweet_count": 8,
          "favorite_count": 28
        }
      }
    },
    "MwnJAnDQ": {
      "sources": {
        "https://twitter.com/Cherryberrii1/status/1424062312130875398": {
          "created_time": "2021-08-07T17:38:07.000Z",
          "retweet_count": 1,
          "favorite_count": 0
        }
      }
    },
    "xnRGrwqQ": {
      "sources": {
        "https://twitter.com/kcurran77/status/1424382612571885574": {
          "created_time": "2021-08-08T14:50:53.000Z",
          "retweet_count": 1,
          "favorite_count": 3
        }
      }
    },
    "MwakNl4Q": {
      "sources": {
        "https://twitter.com/tewlyrally/status/1424804451232075807": {
          "created_time": "2021-08-09T18:47:07.000Z",
          "retweet_count": 0,
          "favorite_count": 0
        }
      }
    },
    "P9W4e4EQ": {
      "sources": {
        "https://twitter.com/Ceiyb_Bae/status/1425089716836347915": {
          "created_time": "2021-08-10T13:40:40.000Z",
          "retweet_count": 0,
          "favorite_count": 0
        },
        "https://twitter.com/FREED0MnotFree/status/1425093417206484998": {
          "created_time": "2021-08-10T13:55:22.000Z",
          "retweet_count": 0,
          "favorite_count": 1
        },
        "https://twitter.com/heartthrob_jk/status/1425101316410462218": {
          "created_time": "2021-08-10T14:26:45.000Z",
          "retweet_count": 0,
          "favorite_count": 0
        }
      }
    }
  }
}