{
  "rooms": {
    "PAJpQB6O": {
      "sources": {
        "https://www.facebook.com/groups/clubhousethailandcommunity/permalink/432601234460372/": {
          "created_time": "2021-02-12T15:47:31+0000"
        }
      }
    },
    "xjYNbZ2o": {
      "sources": {
        "https://www.facebook.com/groups/clubhousethailandcommunity/permalink/434514947602334/": {
          "created_time": "2021-02-16T03:21:48+0000"
        }
      }
    },
    "xjl7aROo": {
      "sources": {
        "https://twitter.com/BedeutenM/status/1364098416574275588": {
          "created_time": "2021-02-23T06:23:00.000Z"
        }
      }
    },
    "PAKNRqDO": {
      "sources": {
        "https://twitter.com/AFTERN00N___TEA/status/1364171108732207105": {
          "created_time": "2021-02-23T11:11:52.000Z"
        },
        "https://twitter.com/ziinnuf/status/1364171100062588928": {
          "created_time": "2021-02-23T11:11:49.000Z"
        },
        "https://twitter.com/jajajha_/status/1364170257099722754": {
          "created_time": "2021-02-23T11:08:29.000Z"
        },
        "https://twitter.com/CMH99_NooNaa/status/1364170079114469376": {
          "created_time": "2021-02-23T11:07:46.000Z"
        },
        "https://twitter.com/mujisakumiro/status/1364169928664780801": {
          "created_time": "2021-02-23T11:07:10.000Z"
        },
        "https://twitter.com/_Kunmee/status/1364169760598986753": {
          "created_time": "2021-02-23T11:06:30.000Z"
        },
        "https://twitter.com/ppimpprow/status/1364169607574032389": {
          "created_time": "2021-02-23T11:05:54.000Z"
        },
        "https://twitter.com/ZIRBX_96/status/1364169232431280136": {
          "created_time": "2021-02-23T11:04:24.000Z"
        },
        "https://twitter.com/Emeniim/status/1364168841777926148": {
          "created_time": "2021-02-23T11:02:51.000Z"
        },
        "https://twitter.com/JB106BEOM/status/1364176205570711556": {
          "created_time": "2021-02-23T11:32:07.000Z"
        },
        "https://twitter.com/Whit_UOY/status/1364173173504176132": {
          "created_time": "2021-02-23T11:20:04.000Z"
        },
        "https://twitter.com/mamybearr/status/1364173120328720384": {
          "created_time": "2021-02-23T11:19:51.000Z"
        },
        "https://twitter.com/niungianu/status/1364176867129888770": {
          "created_time": "2021-02-23T11:34:44.000Z"
        },
        "https://twitter.com/jendream0023/status/1364172765910102016": {
          "created_time": "2021-02-23T11:18:27.000Z"
        }
      }
    },
    "MwEqbXdO": {
      "sources": {
        "https://twitter.com/wnkdnie/status/1364169964823846913": {
          "created_time": "2021-02-23T11:07:19.000Z"
        },
        "https://twitter.com/panwaisgod/status/1364168166746644488": {
          "created_time": "2021-02-23T11:00:10.000Z"
        }
      }
    },
    "PD5E3wXO": {
      "sources": {
        "https://twitter.com/wnpdsuth/status/1364169691992793091": {
          "created_time": "2021-02-23T11:06:14.000Z"
        },
        "https://twitter.com/Arissuka4/status/1364169670601838592": {
          "created_time": "2021-02-23T11:06:09.000Z"
        },
        "https://twitter.com/channphu/status/1364169627413008390": {
          "created_time": "2021-02-23T11:05:58.000Z"
        },
        "https://twitter.com/3k0tumo/status/1364169563181441038": {
          "created_time": "2021-02-23T11:05:43.000Z"
        },
        "https://twitter.com/mormorjungx/status/1364171271282417669": {
          "created_time": "2021-02-23T11:12:30.000Z"
        }
      }
    },
    "MKoEBRro": {
      "sources": {
        "https://twitter.com/panwaisgod/status/1364192741052141568": {
          "created_time": "2021-02-23T12:37:49.000Z"
        },
        "https://twitter.com/panwaisgod/status/1364198505833656325": {
          "created_time": "2021-02-23T13:00:44.000Z"
        },
        "https://twitter.com/panwaisgod/status/1364207440208621571": {
          "created_time": "2021-02-23T13:36:14.000Z"
        }
      }
    },
    "PryYADnO": {
      "sources": {
        "https://twitter.com/mademayday__/status/1364204109184688131": {
          "created_time": "2021-02-23T13:22:59.000Z"
        }
      }
    },
    "M5GnzJAO": {
      "sources": {
        "https://twitter.com/RadzzBear/status/1364214811907682306": {
          "created_time": "2021-02-23T14:05:31.000Z"
        },
        "https://twitter.com/SuMi_AoR/status/1364218194714497025": {
          "created_time": "2021-02-23T14:18:58.000Z"
        },
        "https://twitter.com/rosesocutie/status/1364223365209153542": {
          "created_time": "2021-02-23T14:39:30.000Z"
        }
      }
    },
    "PDjOeZdO": {
      "sources": {
        "https://twitter.com/x_mmiii_x/status/1364221342464102400": {
          "created_time": "2021-02-23T14:31:28.000Z"
        }
      }
    },
    "xoa4Dr6o": {
      "sources": {
        "https://twitter.com/chaeaa17/status/1364226518478589952": {
          "created_time": "2021-02-23T14:52:02.000Z"
        },
        "https://twitter.com/thefernnit/status/1364228190713958400": {
          "created_time": "2021-02-23T14:58:41.000Z"
        }
      }
    },
    "Mwr0rznO": {
      "sources": {
        "https://twitter.com/Ttime63888212/status/1364231300819812357": {
          "created_time": "2021-02-23T15:11:02.000Z"
        },
        "https://twitter.com/Ttime63888212/status/1364239347302604803": {
          "created_time": "2021-02-23T15:43:01.000Z"
        },
        "https://twitter.com/Ttime63888212/status/1364269363017125889": {
          "created_time": "2021-02-23T17:42:17.000Z"
        }
      }
    },
    "MKbdae4o": {
      "sources": {
        "https://twitter.com/deuxoursgracon/status/1364286708301262848": {
          "created_time": "2021-02-23T18:51:13.000Z"
        }
      }
    },
    "M61Ey7No": {
      "sources": {
        "https://twitter.com/Azzkkklooo/status/1364443854099730434": {
          "created_time": "2021-02-24T05:15:39.000Z"
        },
        "https://thaiclubhouse.web.app/submit.html": {
          "created_time": "2021-02-24T05:57:05.000Z"
        }
      }
    },
    "MKjgWJKo": {
      "sources": {
        "https://twitter.com/panwaisgod/status/1364796716734500867": {
          "created_time": "2021-02-25T04:37:48.000Z"
        },
        "https://twitter.com/panwaisgod/status/1364810144266084355": {
          "created_time": "2021-02-25T05:31:09.000Z"
        }
      }
    },
    "xp9K0blO": {
      "sources": {
        "https://twitter.com/chunchunnaphat/status/1364936862532476928": {
          "created_time": "2021-02-25T13:54:41.000Z"
        },
        "https://twitter.com/yxmrxll/status/1364940829702299649": {
          "created_time": "2021-02-25T14:10:27.000Z"
        },
        "https://twitter.com/chunchunnaphat/status/1364949797673779205": {
          "created_time": "2021-02-25T14:46:05.000Z"
        },
        "https://twitter.com/chunchunnaphat/status/1364965716923977729": {
          "created_time": "2021-02-25T15:49:21.000Z"
        }
      }
    },
    "MKzg1qro": {
      "sources": {
        "https://twitter.com/plengming/status/1364971972988465161": {
          "created_time": "2021-02-25T16:14:12.000Z"
        }
      }
    },
    "MdRRdB0o": {
      "sources": {
        "https://twitter.com/pdd____/status/1364991163023859712": {
          "created_time": "2021-02-25T17:30:28.000Z"
        }
      }
    },
    "mJwDEzLO": {
      "sources": {
        "https://twitter.com/Tualeklllll/status/1365016014157619208": {
          "created_time": "2021-02-25T19:09:13.000Z"
        }
      }
    },
    "M65yepYo": {
      "sources": {
        "https://twitter.com/theperlens/status/1365239784537423878": {
          "created_time": "2021-02-26T09:58:24.000Z"
        }
      }
    },
    "MK5Ejzwo": {
      "sources": {
        "https://twitter.com/rukbkppteesud/status/1365283621880295427": {
          "created_time": "2021-02-26T12:52:35.000Z"
        },
        "https://twitter.com/rukbkppteesud/status/1365282653184819200": {
          "created_time": "2021-02-26T12:48:44.000Z"
        }
      }
    },
    "P9DrYG1O": {
      "sources": {
        "https://twitter.com/taosocutee/status/1365303754896011268": {
          "created_time": "2021-02-26T14:12:35.000Z"
        }
      }
    },
    "MwVR36wO": {
      "sources": {
        "https://twitter.com/walterjkun/status/1365313729433202692": {
          "created_time": "2021-02-26T14:52:14.000Z"
        }
      }
    },
    "MwWBLVOO": {
      "sources": {
        "https://twitter.com/stupidlittleo/status/1365335689051574274": {
          "created_time": "2021-02-26T16:19:29.000Z"
        }
      }
    },
    "xqn2eWjo": {
      "sources": {
        "https://twitter.com/Realsmelody/status/1365347144857571329": {
          "created_time": "2021-02-26T17:05:00.000Z"
        },
        "https://twitter.com/Fengwen_/status/1365346864053190658": {
          "created_time": "2021-02-26T17:03:53.000Z"
        },
        "https://twitter.com/Realsmelody/status/1365349684676489217": {
          "created_time": "2021-02-26T17:15:06.000Z"
        }
      }
    },
    "PDOJ6WvO": {
      "sources": {
        "https://twitter.com/anatomybacon/status/1365355633076105216": {
          "created_time": "2021-02-26T17:38:44.000Z"
        },
        "https://twitter.com/anatomybacon/status/1365356888112517121": {
          "created_time": "2021-02-26T17:43:43.000Z"
        },
        "https://twitter.com/anatomybaconn/status/1365356563737681920": {
          "created_time": "2021-02-26T17:42:26.000Z"
        },
        "https://twitter.com/anatomybaconn/status/1365364018832019461": {
          "created_time": "2021-02-26T18:12:03.000Z"
        },
        "https://twitter.com/anatomybacon/status/1365378239242280960": {
          "created_time": "2021-02-26T19:08:34.000Z"
        }
      }
    },
    "xkJYwego": {
      "sources": {
        "https://twitter.com/pdd____/status/1365365537283342338": {
          "created_time": "2021-02-26T18:18:06.000Z"
        },
        "https://twitter.com/pdd____/status/1365366831012225026": {
          "created_time": "2021-02-26T18:23:14.000Z"
        }
      }
    },
    "M5j47wvO": {
      "sources": {
        "https://twitter.com/TheraphosaArt/status/1365524355258617858": {
          "created_time": "2021-02-27T04:49:11.000Z"
        }
      }
    },
    "MdOwDOqo": {
      "sources": {
        "https://twitter.com/520_112626_wuvU/status/1365664367828639751": {
          "created_time": "2021-02-27T14:05:32.000Z"
        }
      }
    },
    "xkaeon7o": {
      "sources": {
        "https://twitter.com/pupoint_/status/1365662142926446597": {
          "created_time": "2021-02-27T13:56:42.000Z"
        }
      }
    },
    "mJWpAlzo": {
      "sources": {
        "https://twitter.com/xxmmx__/status/1365670685725523969": {
          "created_time": "2021-02-27T14:30:39.000Z"
        },
        "https://twitter.com/xxmmx__/status/1365684184879046657": {
          "created_time": "2021-02-27T15:24:17.000Z"
        }
      }
    },
    "MdR5Anyo": {
      "sources": {
        "https://twitter.com/nam_grhnew/status/1365703034072829953": {
          "created_time": "2021-02-27T16:39:11.000Z"
        },
        "https://twitter.com/berlin97__/status/1365702912635064322": {
          "created_time": "2021-02-27T16:38:42.000Z"
        }
      }
    },
    "xov7V9go": {
      "sources": {
        "https://twitter.com/PxTP46/status/1365715527235035142": {
          "created_time": "2021-02-27T17:28:50.000Z"
        }
      }
    },
    "PY65G9EO": {
      "sources": {
        "https://twitter.com/iamkoyjung/status/1365716404029190145": {
          "created_time": "2021-02-27T17:32:19.000Z"
        }
      }
    },
    "MwkDwvQO": {
      "sources": {
        "https://twitter.com/_valentinebubu/status/1365715482465067010": {
          "created_time": "2021-02-27T17:28:39.000Z"
        }
      }
    },
    "Pr9r8O7O": {
      "sources": {
        "https://twitter.com/itSunShine_s/status/1365726323260362752": {
          "created_time": "2021-02-27T18:11:44.000Z"
        },
        "https://twitter.com/itSunShine_s/status/1365741016527998977": {
          "created_time": "2021-02-27T19:10:07.000Z"
        },
        "https://twitter.com/itSunShine_s/status/1365756145583804417": {
          "created_time": "2021-02-27T20:10:14.000Z"
        }
      }
    },
    "xqndb7eo": {
      "sources": {
        "https://twitter.com/praeraya/status/1365952705248649219": {
          "created_time": "2021-02-28T09:11:17.000Z"
        }
      }
    },
    "PAKwl0wO": {
      "sources": {
        "https://twitter.com/Pimmmiiez/status/1366066762249199621": {
          "created_time": "2021-02-28T16:44:31.000Z",
          "retweet_count": 0,
          "favorite_count": 0
        }
      }
    },
    "mJzgAe5O": {
      "sources": {
        "https://twitter.com/bpblinkblink/status/1366105161106481153": {
          "created_time": "2021-02-28T19:17:06.000Z",
          "retweet_count": 1,
          "favorite_count": 0
        }
      }
    },
    "P9nz34XO": {
      "sources": {
        "https://twitter.com/panwaisgod/status/1366128480027504647": {
          "created_time": "2021-02-28T20:49:45.000Z",
          "retweet_count": 0,
          "favorite_count": 0
        },
        "https://twitter.com/panwaisgod/status/1366129980032262144": {
          "created_time": "2021-02-28T20:55:43.000Z",
          "retweet_count": 0,
          "favorite_count": 0
        }
      }
    },
    "MKoyYnEo": {
      "sources": {
        "https://twitter.com/hoonie2205/status/1366384730069897221": {
          "created_time": "2021-03-01T13:48:00.000Z",
          "retweet_count": 0,
          "favorite_count": 0
        },
        "https://twitter.com/sfhadavin/status/1366385035050315782": {
          "created_time": "2021-03-01T13:49:13.000Z",
          "retweet_count": 0,
          "favorite_count": 1
        }
      }
    },
    "mabz36No": {
      "sources": {
        "https://twitter.com/l_xiaozhan0504/status/1366405772398063625": {
          "created_time": "2021-03-01T15:11:37.000Z",
          "retweet_count": 0,
          "favorite_count": 0
        }
      }
    },
    "xjW5zZwo": {
      "sources": {
        "https://twitter.com/onyourwan/status/1366435802901667840": {
          "created_time": "2021-03-01T17:10:57.000Z",
          "retweet_count": 0,
          "favorite_count": 0
        },
        "https://twitter.com/nam_grhnew/status/1366454205192433668": {
          "created_time": "2021-03-01T18:24:04.000Z",
          "retweet_count": 0,
          "favorite_count": 0
        },
        "https://twitter.com/onyourwan/status/1366455796788203520": {
          "created_time": "2021-03-01T18:30:24.000Z",
          "retweet_count": 0,
          "favorite_count": 0
        },
        "https://twitter.com/nongpoploy/status/1366467609466724353": {
          "created_time": "2021-03-01T19:17:20.000Z",
          "retweet_count": 0,
          "favorite_count": 0
        },
        "https://twitter.com/nam_grhnew/status/1366467034368811008": {
          "created_time": "2021-03-01T19:15:03.000Z",
          "retweet_count": 0,
          "favorite_count": 0
        },
        "https://twitter.com/nam_grhnew/status/1366466837710430208": {
          "created_time": "2021-03-01T19:14:16.000Z",
          "retweet_count": 0,
          "favorite_count": 0
        }
      }
    }
  }
}