{
  "rooms": {
    "xpYdjaAg": {
      "sources": {
        "https://www.facebook.com/groups/clubhousethailandcommunity/permalink/434145954305900/": {
          "created_time": "2021-02-15T10:54:53+0000"
        }
      }
    },
    "PG2BeAeg": {
      "sources": {
        "https://www.facebook.com/groups/clubhousethailandcommunity/permalink/434646680922494/?comment_id=434649470922215": {
          "created_time": "2021-02-16T10:05:20+0000"
        }
      }
    },
    "m3lWzWQG": {
      "sources": {
        "https://twitter.com/panwaisgod/status/1364141741419323393": {
          "created_time": "2021-02-23T09:15:10.000Z"
        },
        "https://twitter.com/panwaisgod/status/1364140988881530883": {
          "created_time": "2021-02-23T09:12:10.000Z"
        }
      }
    },
    "xnbnbpOg": {
      "sources": {
        "https://twitter.com/_pppppppppn_/status/1364147193565769729": {
          "created_time": "2021-02-23T09:36:50.000Z"
        }
      }
    },
    "xVbO983G": {
      "sources": {
        "https://twitter.com/chunchunnaphat/status/1364196690098487297": {
          "created_time": "2021-02-23T12:53:31.000Z"
        }
      }
    },
    "xjX7dDvg": {
      "sources": {
        "https://twitter.com/babywinky_/status/1364209930505310219": {
          "created_time": "2021-02-23T13:46:07.000Z"
        },
        "https://twitter.com/babywinky_/status/1364209541802430464": {
          "created_time": "2021-02-23T13:44:35.000Z"
        }
      }
    },
    "PYBBo29G": {
      "sources": {
        "https://twitter.com/k_ksd123/status/1364215533239894020": {
          "created_time": "2021-02-23T14:08:23.000Z"
        }
      }
    },
    "xe2651XG": {
      "sources": {
        "https://twitter.com/jaejin_120/status/1364218407965446151": {
          "created_time": "2021-02-23T14:19:49.000Z"
        }
      }
    },
    "xe6bl76G": {
      "sources": {
        "https://twitter.com/May_scap/status/1364256018339823616": {
          "created_time": "2021-02-23T16:49:16.000Z"
        }
      }
    },
    "xV6EKKqG": {
      "sources": {
        "https://twitter.com/Fengwen_/status/1364259424206921729": {
          "created_time": "2021-02-23T17:02:48.000Z"
        },
        "https://twitter.com/Fengwen_/status/1364260323595706370": {
          "created_time": "2021-02-23T17:06:22.000Z"
        },
        "https://twitter.com/Fengwen_/status/1364284119589425152": {
          "created_time": "2021-02-23T18:40:55.000Z"
        },
        "https://twitter.com/Realsmelody/status/1364283846770921474": {
          "created_time": "2021-02-23T18:39:50.000Z"
        },
        "https://twitter.com/Realsmelody/status/1364289087306276869": {
          "created_time": "2021-02-23T19:00:40.000Z"
        }
      }
    },
    "xpYJrpZg": {
      "sources": {
        "https://twitter.com/awds4596/status/1364275007648456705": {
          "created_time": "2021-02-23T18:04:43.000Z"
        }
      }
    }
  }
}